Workbook

Sheet Legend
A1: Dell Technologies Integration - Value Creation Integration Office (VCIO)
A2: Dell Inc. and EMC Corporation | Reporting week W3 (26 - 30 September 2016) | Day 22 after Day 1 | Close 7 September 2016
A4: How to use this workbook
A5: 1. Baseline is locked and read only. It was signed off before Day 1.
A6: 2. Synergy Register: one row per initiative. Target, secured and realised are entered per initiative, never at bucket level.
A7: 3. Only Finance-validated initiatives count towards the reportable secured figure, per Steering Committee decision B-06.
A8: 4. Phasing carries the in-year effect for the current financial year and cross-checks back to the register.
A9: 5. Summary rolls up by bucket and reconciles to the deal model. No input.
A11: Conventions and assumptions
A12: Reporting week W3 (26 - 30 September 2016), day 22 after Day 1.
A13: All amounts in USD million unless the column header says otherwise.
A14: Run-rate is the annualised effect once fully implemented. In-year is the effect landing in the current financial year.
... A24: Synthetic workbook. All operational names, figures, risks and synergy values are invented and internally consistent; they are not a representation of what any party actually did.

Sheet Baseline
A1: Locked Financial Baseline
A2: Baseline as at Day 1 (7 September 2016) | signed off 2 September 2016 | do not edit
A4: Baseline ID | B4: Line item | C4: Entity | D4: Cost category | E4: FY16 actual (USD m) | F4: FY17 budget (USD m) | G4: Source document
A5: BL-01 | B5: External IT maintenance and software licences | C5: EMC Corporation | D5: IT cost | E5: 1840 | F5: 1912 | G5: Target FY16 statutory accounts, note 14
A6: BL-02 | B6: Data centre hosting and co-location | C6: EMC Corporation | D6: IT cost | E6: 742 | F6: 768 | G6: Target FY16 statutory accounts, note 14
A7: BL-03 | B7: Indirect procurement, addressable spend | C7: Combined | D7: Procurement | E7: 4310 | F7: 4402 | G7: Combined spend cube, wave 1 extract
A8: BL-04 | B8: Logistics and freight | C8: Combined | D8: Procurement | E8: 1965 | F8: 2018 | G8: Combined spend cube, wave 1 extract
A9: BL-05 | B9: Component sourcing, addressable bill of materials | C9: Combined | D9: Procurement | E9: 6120 | F9: 6244 | G9: Combined spend cube, wave 1 extract
A10: BL-06 | B10: Corporate and shared service personnel cost | C10: Combined | D10: Personnel | E10: 2874 | F10: 2951 | G10: Combined FY17 operating plan
A11: BL-07 | B11: Sales compensation, plan cost | C11: Combined | D11: Personnel | E11: 1638 | F11: 1702 | G11: Combined FY17 operating plan
A12: BL-08 | B12: Property lease and facilities cost | C12: Combined | D12: Footprint | E12: 884 | F12: 903 | G12: Combined lease register, September 2016
A13: BL-09 | B13: Warehouse and distribution operating cost | C13: Combined | D13: Operations | E13: 612 | F13: 628 | G13: Combined FY17 operating plan
A14: BL-10 | B14: Marketing and events | C14: Combined | D14: Operations | E14: 428 | F14: 441 | G14: Combined FY17 operating plan

Sheet Synergy Register
A1: Synergy Register
A2: One row per initiative | 16 initiatives | status 28 September 2016 | target USD 7,252 m run-rate
A4: Initiative ID | B4: Initiative | C4: Bucket | D4: Type | E4: Workstream | F4: Owner | G4: Target run-rate (USD m) | H4: Secured run-rate (USD m) | I4: Realised to date (USD m) | J4: Secured % | K4: FY17 in-year (USD m) | L4: Cost to achieve (USD m) | M4: Status | N4: Finance validated
A5: S-01 | B5: Consolidate indirect procurement onto combined contracts | C5: Procurement | D5: Cost | E5: WS5 Supply Chain | F5: K. Matsuda | G5: 310 | H5: 214 | I5: 42 | J5: =IFERROR(H5/G5,"") -> 0.69032258 | K5: 96 | L5: 38 | M5: In progress | N5: Yes
A6: S-02 | B6: Renegotiate logistics and freight with the top 12 providers | C6: Procurement | D6: Cost | E6: WS5 Supply Chain | F6: K. Matsuda | G6: 245 | H6: 118 | I6: 0 | J6: =IFERROR(H6/G6,"") -> 0.48163265 | K6: 44 | L6: 21 | M6: In progress | N6: Yes
A7: S-03 | B7: Consolidate component sourcing across the combined bill of materials | C7: Procurement | D7: Cost | E7: WS5 Supply Chain | F7: K. Matsuda | G7: 268 | H7: 96 | I7: 0 | J7: =IFERROR(H7/G7,"") -> 0.35820896 | K7: 31 | L7: 26 | M7: Approved | N7: No
A8: S-04 | B8: Rationalise overlapping enterprise software licences | C8: IT cost | D8: Cost | E8: WS3 IT | F8: T. Bergström | G8: 186 | H8: 141 | I8: 28 | J8: =IFERROR(H8/G8,"") -> 0.75806452 | K8: 62 | L8: 34 | M8: In progress | N8: Yes
A9: S-05 | B9: Consolidate data centre footprint and hosting contracts | C9: IT cost | D9: Cost | E9: WS3 IT | F9: T. Bergström | G9: 152 | H9: 61 | I9: 0 | J9: =IFERROR(H9/G9,"") -> 0.40131579 | K9: 18 | L9: 44 | M9: Approved | N9: No
A10: S-06 | B10: Merge service desk and IT operations tooling | C10: IT cost | D10: Cost | E10: WS3 IT | F10: T. Bergström | G10: 74 | H10: 22 | I10: 0 | J10: =IFERROR(H10/G10,"") -> 0.2972973 | K10: 6 | L10: 12 | M10: Business case | N10: No
A11: S-07 | B11: Remove duplicated corporate and shared service functions | C11: Personnel | D11: Cost | E11: WS4 Human Capital | F11: J. Adeyemi | G11: 296 | H11: 148 | I11: 31 | J11: =IFERROR(H11/G11,"") -> 0.5 | K11: 74 | L11: 96 | M11: In progress | N11: Yes
A12: S-08 | B12: Harmonise sales compensation and reduce plan complexity | C12: Personnel | D12: Cost | E12: WS4 Human Capital | F12: J. Adeyemi | G12: 118 | H12: 47 | I12: 0 | J12: =IFERROR(H12/G12,"") -> 0.39830508 | K12: 14 | L12: 18 | M12: Approved | N12: No
A13: S-09 | B13: Consolidate offices where both groups hold leases in one city | C13: Footprint | D13: Cost | E13: WS7 Real Estate | F13: F. Ricciardi | G13: 134 | H13: 52 | I13: 9 | J13: =IFERROR(H13/G13,"") -> 0.3880597 | K13: 22 | L13: 41 | M13: In progress | N13: Yes
A14: S-10 | B14: Consolidate warehouse and distribution network in EMEA and APJ | C14: Operations | D14: Cost | E14: WS5 Supply Chain | F14: K. Matsuda | G14: 97 | H14: 24 | I14: 0 | J14: =IFERROR(H14/G14,"") -> 0.24742268 | K14: 8 | L14: 29 | M14: Business case | N14: No
A15: S-11 | B15: Rationalise marketing spend and event portfolio | C15: Operations | D15: Cost | E15: WS6 Go-to-Market | F15: L. Kowalczyk | G15: 62 | H15: 38 | I15: 11 | J15: =IFERROR(H15/G15,"") -> 0.61290323 | K15: 19 | L15: 7 | M15: In progress | N15: Yes
A16: S-12 | B16: Cross-sell infrastructure portfolio into the client installed base | C16: Revenue cross-sell | D16: Revenue | E16: WS6 Go-to-Market | F16: L. Kowalczyk | G16: 2240 | H16: 610 | I16: 0 | J16: =IFERROR(H16/G16,"") -> 0.27232143 | K16: 148 | L16: 74 | M16: In progress | N16: No
... A20: S-16 | B20: Harmonise discount governance across the combined portfolio | C20: Revenue pricing | D20: Revenue | E20: WS6 Go-to-Market | F20: R. Whitfield | G20: 210 | H20: 61 | I20: 0 | J20: =IFERROR(H20/G20,"") -> 0.29047619 | K20: 14 | L20: 9 | M20: Approved | N20: No
B21: Total | G21: =SUM(G5:G20) -> 7252 | H21: =SUM(H5:H20) -> 2354 | I21: =SUM(I5:I20) -> 121 | J21: =IFERROR(H21/G21,"") -> 0.32460011 | K21: =SUM(K5:K20) -> 727 | L21: =SUM(L5:L20) -> 565

Sheet Phasing
A1: In-Year Phasing, current financial year
A2: Monthly in-year effect per initiative in USD million, cross-checked against the register
A4: Initiative ID | B4: Initiative | C4: Sep 16 | D4: Oct 16 | E4: Nov 16 | F4: Dec 16 | G4: Jan 17 | H4: Feb 17 | I4: Total | J4: Check vs. register
A5: S-01 | B5: Consolidate indirect procurement onto combined con | C5: 0 | D5: 6 | E5: 13 | F5: 19 | G5: 26 | H5: 32 | I5: =SUM(C5:H5) -> 96 | J5: =IF(I5=INDEX('Synergy Register'!$K$5:$K$20,MATCH($A5,'Synergy Register'!$A$5:$A$20,0)),"ok","check") -> ok
A6: S-02 | B6: Renegotiate logistics and freight with the top 12 | C6: 0 | D6: 3 | E6: 6 | F6: 9 | G6: 12 | H6: 14 | I6: =SUM(C6:H6) -> 44 | J6: =IF(I6=INDEX('Synergy Register'!$K$5:$K$20,MATCH($A6,'Synergy Register'!$A$5:$A$20,0)),"ok","check") -> ok
A7: S-03 | B7: Consolidate component sourcing across the combined | C7: 0 | D7: 2 | E7: 4 | F7: 6 | G7: 8 | H7: 11 | I7: =SUM(C7:H7) -> 31 | J7: =IF(I7=INDEX('Synergy Register'!$K$5:$K$20,MATCH($A7,'Synergy Register'!$A$5:$A$20,0)),"ok","check") -> ok
A8: S-04 | B8: Rationalise overlapping enterprise software licenc | C8: 0 | D8: 4 | E8: 8 | F8: 12 | G8: 17 | H8: 21 | I8: =SUM(C8:H8) -> 62 | J8: =IF(I8=INDEX('Synergy Register'!$K$5:$K$20,MATCH($A8,'Synergy Register'!$A$5:$A$20,0)),"ok","check") -> ok
A9: S-05 | B9: Consolidate data centre footprint and hosting cont | C9: 0 | D9: 1 | E9: 2 | F9: 4 | G9: 5 | H9: 6 | I9: =SUM(C9:H9) -> 18 | J9: =IF(I9=INDEX('Synergy Register'!$K$5:$K$20,MATCH($A9,'Synergy Register'!$A$5:$A$20,0)),"ok","check") -> ok
A10: S-06 | B10: Merge service desk and IT operations tooling | C10: 0 | D10: 0 | E10: 1 | F10: 1 | G10: 2 | H10: 2 | I10: =SUM(C10:H10) -> 6 | J10: =IF(I10=INDEX('Synergy Register'!$K$5:$K$20,MATCH($A10,'Synergy Register'!$A$5:$A$20,0)),"ok","check") -> ok
A11: S-07 | B11: Remove duplicated corporate and shared service fun | C11: 0 | D11: 5 | E11: 10 | F11: 15 | G11: 20 | H11: 24 | I11: =SUM(C11:H11) -> 74 | J11: =IF(I11=INDEX('Synergy Register'!$K$5:$K$20,MATCH($A11,'Synergy Register'!$A$5:$A$20,0)),"ok","check") -> ok
A12: S-08 | B12: Harmonise sales compensation and reduce plan compl | C12: 0 | D12: 1 | E12: 2 | F12: 3 | G12: 4 | H12: 4 | I12: =SUM(C12:H12) -> 14 | J12: =IF(I12=INDEX('Synergy Register'!$K$5:$K$20,MATCH($A12,'Synergy Register'!$A$5:$A$20,0)),"ok","check") -> ok
A13: S-09 | B13: Consolidate offices where both groups hold leases | C13: 0 | D13: 1 | E13: 3 | F13: 4 | G13: 6 | H13: 8 | I13: =SUM(C13:H13) -> 22 | J13: =IF(I13=INDEX('Synergy Register'!$K$5:$K$20,MATCH($A13,'Synergy Register'!$A$5:$A$20,0)),"ok","check") -> ok
A14: S-10 | B14: Consolidate warehouse and distribution network in | C14: 0 | D14: 1 | E14: 1 | F14: 2 | G14: 2 | H14: 2 | I14: =SUM(C14:H14) -> 8 | J14: =IF(I14=INDEX('Synergy Register'!$K$5:$K$20,MATCH($A14,'Synergy Register'!$A$5:$A$20,0)),"ok","check") -> ok
A15: S-11 | B15: Rationalise marketing spend and event portfolio | C15: 0 | D15: 1 | E15: 3 | F15: 4 | G15: 5 | H15: 6 | I15: =SUM(C15:H15) -> 19 | J15: =IF(I15=INDEX('Synergy Register'!$K$5:$K$20,MATCH($A15,'Synergy Register'!$A$5:$A$20,0)),"ok","check") -> ok
A16: S-12 | B16: Cross-sell infrastructure portfolio into the clien | C16: 0 | D16: 10 | E16: 20 | F16: 30 | G16: 39 | H16: 49 | I16: =SUM(C16:H16) -> 148 | J16: =IF(I16=INDEX('Synergy Register'!$K$5:$K$20,MATCH($A16,'Synergy Register'!$A$5:$A$20,0)),"ok","check") -> ok
... A20: S-16 | B20: Harmonise discount governance across the combined | C20: 0 | D20: 1 | E20: 2 | F20: 3 | G20: 4 | H20: 4 | I20: =SUM(C20:H20) -> 14 | J20: =IF(I20=INDEX('Synergy Register'!$K$5:$K$20,MATCH($A20,'Synergy Register'!$A$5:$A$20,0)),"ok","check") -> ok
B21: Total in-year effect | C21: =SUM(C5:C20) -> 0 | D21: =SUM(D5:D20) -> 47 | E21: =SUM(E5:E20) -> 98 | F21: =SUM(F5:F20) -> 146 | G21: =SUM(G5:G20) -> 196 | H21: =SUM(H5:H20) -> 240 | I21: =SUM(I5:I20) -> 727

Sheet Cost to Achieve
A1: Cost to Achieve
A2: One-off cost required to deliver each initiative | total USD 565 m
A4: CTA ID | B4: Initiative ID | C4: Cost item | D4: Cost type | E4: Owner | F4: Budgeted (USD m) | G4: Committed (USD m) | H4: Spent (USD m) | I4: Remaining (USD m)
A5: CTA-01 | B5: S-01 | C5: Delivery cost for Consolidate indirect procurement onto combined | D5: Internal effort | E5: K. Matsuda | F5: 38 | G5: 27 | H5: 10 | I5: =F5-H5 -> 28
A6: CTA-02 | B6: S-02 | C6: Delivery cost for Renegotiate logistics and freight with the top | D6: Internal effort | E6: K. Matsuda | F6: 21 | G6: 15 | H6: 5 | I6: =F6-H6 -> 16
A7: CTA-03 | B7: S-03 | C7: Delivery cost for Consolidate component sourcing across the comb | D7: Internal effort | E7: K. Matsuda | F7: 26 | G7: 18 | H7: 6 | I7: =F7-H7 -> 20
A8: CTA-04 | B8: S-04 | C8: Delivery cost for Rationalise overlapping enterprise software li | D8: External advisory | E8: T. Bergström | F8: 34 | G8: 24 | H8: 8 | I8: =F8-H8 -> 26
A9: CTA-05 | B9: S-05 | C9: Delivery cost for Consolidate data centre footprint and hosting | D9: External advisory | E9: T. Bergström | F9: 44 | G9: 31 | H9: 11 | I9: =F9-H9 -> 33
A10: CTA-06 | B10: S-06 | C10: Delivery cost for Merge service desk and IT operations tooling | D10: External advisory | E10: T. Bergström | F10: 12 | G10: 8 | H10: 3 | I10: =F10-H10 -> 9
A11: CTA-07 | B11: S-07 | C11: Delivery cost for Remove duplicated corporate and shared service | D11: Severance | E11: J. Adeyemi | F11: 96 | G11: 67 | H11: 24 | I11: =F11-H11 -> 72
A12: CTA-08 | B12: S-08 | C12: Delivery cost for Harmonise sales compensation and reduce plan c | D12: Severance | E12: J. Adeyemi | F12: 18 | G12: 13 | H12: 4 | I12: =F12-H12 -> 14
A13: CTA-09 | B13: S-09 | C13: Delivery cost for Consolidate offices where both groups hold lea | D13: Site exit | E13: F. Ricciardi | F13: 41 | G13: 29 | H13: 10 | I13: =F13-H13 -> 31
A14: CTA-10 | B14: S-10 | C14: Delivery cost for Consolidate warehouse and distribution network | D14: Internal effort | E14: K. Matsuda | F14: 29 | G14: 20 | H14: 7 | I14: =F14-H14 -> 22
A15: CTA-11 | B15: S-11 | C15: Delivery cost for Rationalise marketing spend and event portfoli | D15: Internal effort | E15: L. Kowalczyk | F15: 7 | G15: 5 | H15: 2 | I15: =F15-H15 -> 5
A16: CTA-12 | B16: S-12 | C16: Delivery cost for Cross-sell infrastructure portfolio into the c | D16: Enablement | E16: L. Kowalczyk | F16: 74 | G16: 52 | H16: 18 | I16: =F16-H16 -> 56
... A20: CTA-16 | B20: S-16 | C20: Delivery cost for Harmonise discount governance across the combi | D20: Enablement | E20: R. Whitfield | F20: 9 | G20: 6 | H20: 2 | I20: =F20-H20 -> 7
C21: Total | F21: =SUM(F5:F20) -> 565 | G21: =SUM(G5:G20) -> 396 | H21: =SUM(H5:H20) -> 139 | I21: =SUM(I5:I20) -> 426

Sheet Summary
A1: Synergy Summary by Bucket
A2: Calculates automatically from the register and the cost to achieve tab. No input.
A5: Bucket | B5: Initiatives | C5: Target (USD m) | D5: Secured (USD m) | E5: Secured % | F5: FY17 in-year (USD m) | G5: Cost to achieve (USD m)
A6: Procurement | B6: =COUNTIF('Synergy Register'!$C$5:$C$20,$A6) -> 3 | C6: =SUMIF('Synergy Register'!$C$5:$C$20,$A6,'Synergy Register'!$G$5:$G$20) -> 823 | D6: =SUMIF('Synergy Register'!$C$5:$C$20,$A6,'Synergy Register'!$H$5:$H$20) -> 428 | E6: =IFERROR($D6/$C6,"") -> 0.5200486 | F6: =SUMIF('Synergy Register'!$C$5:$C$20,$A6,'Synergy Register'!$K$5:$K$20) -> 171 | G6: =SUMIF('Synergy Register'!$C$5:$C$20,$A6,'Synergy Register'!$L$5:$L$20) -> 85
A7: IT cost | B7: =COUNTIF('Synergy Register'!$C$5:$C$20,$A7) -> 3 | C7: =SUMIF('Synergy Register'!$C$5:$C$20,$A7,'Synergy Register'!$G$5:$G$20) -> 412 | D7: =SUMIF('Synergy Register'!$C$5:$C$20,$A7,'Synergy Register'!$H$5:$H$20) -> 224 | E7: =IFERROR($D7/$C7,"") -> 0.54368932 | F7: =SUMIF('Synergy Register'!$C$5:$C$20,$A7,'Synergy Register'!$K$5:$K$20) -> 86 | G7: =SUMIF('Synergy Register'!$C$5:$C$20,$A7,'Synergy Register'!$L$5:$L$20) -> 90
A8: Personnel | B8: =COUNTIF('Synergy Register'!$C$5:$C$20,$A8) -> 2 | C8: =SUMIF('Synergy Register'!$C$5:$C$20,$A8,'Synergy Register'!$G$5:$G$20) -> 414 | D8: =SUMIF('Synergy Register'!$C$5:$C$20,$A8,'Synergy Register'!$H$5:$H$20) -> 195 | E8: =IFERROR($D8/$C8,"") -> 0.47101449 | F8: =SUMIF('Synergy Register'!$C$5:$C$20,$A8,'Synergy Register'!$K$5:$K$20) -> 88 | G8: =SUMIF('Synergy Register'!$C$5:$C$20,$A8,'Synergy Register'!$L$5:$L$20) -> 114
A9: Footprint | B9: =COUNTIF('Synergy Register'!$C$5:$C$20,$A9) -> 1 | C9: =SUMIF('Synergy Register'!$C$5:$C$20,$A9,'Synergy Register'!$G$5:$G$20) -> 134 | D9: =SUMIF('Synergy Register'!$C$5:$C$20,$A9,'Synergy Register'!$H$5:$H$20) -> 52 | E9: =IFERROR($D9/$C9,"") -> 0.3880597 | F9: =SUMIF('Synergy Register'!$C$5:$C$20,$A9,'Synergy Register'!$K$5:$K$20) -> 22 | G9: =SUMIF('Synergy Register'!$C$5:$C$20,$A9,'Synergy Register'!$L$5:$L$20) -> 41
A10: Operations | B10: =COUNTIF('Synergy Register'!$C$5:$C$20,$A10) -> 2 | C10: =SUMIF('Synergy Register'!$C$5:$C$20,$A10,'Synergy Register'!$G$5:$G$20) -> 159 | D10: =SUMIF('Synergy Register'!$C$5:$C$20,$A10,'Synergy Register'!$H$5:$H$20) -> 62 | E10: =IFERROR($D10/$C10,"") -> 0.38993711 | F10: =SUMIF('Synergy Register'!$C$5:$C$20,$A10,'Synergy Register'!$K$5:$K$20) -> 27 | G10: =SUMIF('Synergy Register'!$C$5:$C$20,$A10,'Synergy Register'!$L$5:$L$20) -> 36
A11: Revenue cross-sell | B11: =COUNTIF('Synergy Register'!$C$5:$C$20,$A11) -> 3 | C11: =SUMIF('Synergy Register'!$C$5:$C$20,$A11,'Synergy Register'!$G$5:$G$20) -> 4680 | D11: =SUMIF('Synergy Register'!$C$5:$C$20,$A11,'Synergy Register'!$H$5:$H$20) -> 1248 | E11: =IFERROR($D11/$C11,"") -> 0.26666667 | F11: =SUMIF('Synergy Register'!$C$5:$C$20,$A11,'Synergy Register'!$K$5:$K$20) -> 302 | G11: =SUMIF('Synergy Register'!$C$5:$C$20,$A11,'Synergy Register'!$L$5:$L$20) -> 157
A12: Revenue pricing | B12: =COUNTIF('Synergy Register'!$C$5:$C$20,$A12) -> 2 | C12: =SUMIF('Synergy Register'!$C$5:$C$20,$A12,'Synergy Register'!$G$5:$G$20) -> 630 | D12: =SUMIF('Synergy Register'!$C$5:$C$20,$A12,'Synergy Register'!$H$5:$H$20) -> 145 | E12: =IFERROR($D12/$C12,"") -> 0.23015873 | F12: =SUMIF('Synergy Register'!$C$5:$C$20,$A12,'Synergy Register'!$K$5:$K$20) -> 31 | G12: =SUMIF('Synergy Register'!$C$5:$C$20,$A12,'Synergy Register'!$L$5:$L$20) -> 42
A13: Total | B13: =SUM(B6:B12) -> 16 | C13: =SUM(C6:C12) -> 7252 | D13: =SUM(D6:D12) -> 2354 | E13: =IFERROR($D13/$C13,"") -> 0.32460011 | F13: =SUM(F6:F12) -> 727 | G13: =SUM(G6:G12) -> 565
A15: Reconciliation to the deal model
A16: Deal model target (USD m run-rate) | B16: 8000
A17: Total target in register (USD m) | B17: =$C$13 -> 7252
A18: Gap to deal model (USD m) | B18: =$B$16-$B$17 -> 748
A19: Secured, all initiatives (USD m) | B19: =$D$13 -> 2354
A20: Secured, Finance validated only (USD m) | B20: =SUMIF('Synergy Register'!$N$5:$N$20,"Yes",'Synergy Register'!$H$5:$H$20) -> 711
A21: Difference, not yet validated (USD m) | B21: =$B$19-$B$20 -> 1643
A22: Cost synergy target (USD m) | B22: =SUMIF('Synergy Register'!$D$5:$D$20,"Cost",'Synergy Register'!$G$5:$G$20) -> 1942
A23: Revenue synergy target (USD m) | B23: =SUMIF('Synergy Register'!$D$5:$D$20,"Revenue",'Synergy Register'!$G$5:$G$20) -> 5310
A24: Revenue to cost ratio | B24: =IFERROR($B$23/$B$22,"") -> 2.7342945
A26: Decision B-06: only the Finance-validated figure is reported to the Steering Committee from session 02 onward.
