Workbook

Sheet Legend
A1: Dell Technologies Integration - Value Creation Integration Office (VCIO)
A2: Dell Inc. and EMC Corporation | Reporting week W3 (26 - 30 September 2016) | Day 22 after Day 1 | Close 7 September 2016
A4: How to use this workbook
A5: 1. One tab per RAID category: Risks, Assumptions, Issues, Dependencies.
A6: 2. A risk becomes an issue only once it has materialised. Move the row, keep the originating risk ID.
A7: 3. Severity is calculated as likelihood times impact. Do not type it.
A8: 4. Severity 15 and above escalates to the Steering Committee, per the integration charter.
A9: 5. The Summary tab calculates automatically. Do not overwrite formulas.
A11: Conventions and assumptions
A12: Reporting week W3 (26 - 30 September 2016), day 22 after Day 1 (7 September 2016).
A13: Likelihood and impact scored 1 to 5. Bands: 1 to 6 Low, 8 to 12 Medium, 15 to 20 High, 25 Critical.
A14: Date format DD.MM.YYYY throughout.
... A22: Synthetic workbook. All operational names, figures, risks and synergy values are invented and internally consistent; they are not a representation of what any party actually did.

Sheet Risks
A1: Risk Register
A2: Status 29 September 2016 | 14 open risks | 3 at or above severity 15 | Owner: Value Creation Integration Office (VCIO)
A4: Risk ID | B4: Risk description | C4: Workstream | D4: Owner | E4: Likelihood | F4: Impact | G4: Severity | H4: Band | I4: Mitigation action | J4: Due date | K4: Status | L4: Trend | M4: Escalated to
A5: R-01 | B5: Legacy ERP upgrade at the target collides with the integration design, delaying the consolidation blueprint | C5: WS3 IT | D5: T. Bergström | E5: 4 | F5: 5 | G5: =E5*F5 -> 20 | H5: =IF(G5>=25,"Critical",IF(G5>=15,"High",IF(G5>=8,"Medium","Low"))) -> High | I5: Freeze the legacy upgrade scope, run a joint architecture session, resequence the blueprint against the Day 100 commitment | J5: 42657 | K5: Open | L5: Increasing | M5: Steering Committee
A6: R-02 | B6: Works council consultation in Germany does not conclude before the organisation announcement, blocking the structure release | C6: WS4 Human Capital | D6: W. Kempowski | E6: 4 | F6: 3 | G6: =E6*F6 -> 12 | H6: =IF(G6>=25,"Critical",IF(G6>=15,"High",IF(G6>=8,"Medium","Low"))) -> Medium | I6: Weekly alignment with the works council chair, prepare a reduced announcement scope that excludes co-determined units | J6: 42664 | K6: Open | L6: Increasing | M6: VCIO
A7: R-03 | B7: Master data quality in the supplier and material records prevents a clean migration dry run | C7: WS3 IT | D7: G. Aydin | E7: 4 | F7: 4 | G7: =E7*F7 -> 16 | H7: =IF(G7>=25,"Critical",IF(G7>=15,"High",IF(G7>=8,"Medium","Low"))) -> High | I7: Re-extract with a corrected field mapping, add a data quality gate before each migration wave | J7: 42648 | K7: In progress | L7: Stable | M7: VCIO
A8: R-04 | B8: Key talent attrition in the combined field organisation before the coverage model is in force | C8: WS4 Human Capital | D8: J. Adeyemi | E8: 3 | F8: 5 | G8: =E8*F8 -> 15 | H8: =IF(G8>=25,"Critical",IF(G8>=15,"High",IF(G8>=8,"Medium","Low"))) -> High | I8: Confirm retention packages for named critical roles, bring the coverage model communication forward | J8: 42650 | K8: In progress | L8: Stable | M8: Steering Committee
A9: R-05 | B9: Customer confusion during the portfolio transition depresses the net promoter score ahead of the flagship event | C9: WS6 Go-to-Market | D9: L. Kowalczyk | E9: 3 | F9: 4 | G9: =E9*F9 -> 12 | H9: =IF(G9>=25,"Critical",IF(G9>=15,"High",IF(G9>=8,"Medium","Low"))) -> Medium | I9: Publish the portfolio cross-reference, brief the field with the e-runbook, measure the NPS baseline before the event | J9: 42654 | K9: In progress | L9: Decreasing
A10: R-06 | B10: Entity rationalisation slips and delays the transfer pricing model, creating an exposure at the first combined year end | C10: WS2 Tax | D10: N. Devereux | E10: 3 | F10: 4 | G10: =E10*F10 -> 12 | H10: =IF(G10>=25,"Critical",IF(G10>=15,"High",IF(G10>=8,"Medium","Low"))) -> Medium | I10: Escalate the entity chain review, run the transfer pricing outline in parallel rather than in sequence | J10: 42664 | K10: Open | L10: Increasing | M10: Steering Committee
A11: R-07 | B11: Interdependencies between workstreams are not visible to the teams that create them | C11: WS3 IT | D11: D. Okonjo | E11: 4 | F11: 3 | G11: =E11*F11 -> 12 | H11: =IF(G11>=25,"Critical",IF(G11>=15,"High",IF(G11>=8,"Medium","Low"))) -> Medium | I11: Refresh the dependency map weekly, require both leads to confirm every handover date in the register | J11: 42643 | K11: In progress | L11: Decreasing
A12: R-08 | B12: Supplier renegotiation slips past the wave 1 window and the procurement synergy lands in the following financial year | C12: WS5 Supply Chain | D12: K. Matsuda | E12: 3 | F12: 3 | G12: =E12*F12 -> 9 | H12: =IF(G12>=25,"Critical",IF(G12>=15,"High",IF(G12>=8,"Medium","Low"))) -> Medium | I12: Open negotiations with the top 12 logistics providers before the spend cube is complete rather than after | J12: 42671 | K12: Open | L12: Stable
A13: R-09 | B13: Two sales organisations continue to call on the same accounts before territory alignment takes effect | C13: WS6 Go-to-Market | D13: L. Kowalczyk | E13: 3 | F13: 3 | G13: =E13*F13 -> 9 | H13: =IF(G13>=25,"Critical",IF(G13>=15,"High",IF(G13>=8,"Medium","Low"))) -> Medium | I13: Interim account ownership list published weekly until the coverage model is in force | J13: 42657 | K13: In progress | L13: Stable
A14: R-10 | B14: Site consolidation assumptions rest on lease data that is not yet complete for all EMEA locations | C14: WS7 Real Estate | D14: F. Ricciardi | E14: 3 | F14: 2 | G14: =E14*F14 -> 6 | H14: =IF(G14>=25,"Critical",IF(G14>=15,"High",IF(G14>=8,"Medium","Low"))) -> Low | I14: Complete the lease expiry analysis for the remaining sites before the plan is approved | J14: 42664 | K14: Open | L14: Stable
A15: R-11 | B15: Debt service constrains discretionary integration spend below the level the plan assumes | C15: WS1 Finance | D15: R. Whitfield | E15: 2 | F15: 5 | G15: =E15*F15 -> 10 | H15: =IF(G15>=25,"Critical",IF(G15>=15,"High",IF(G15>=8,"Medium","Low"))) -> Medium | I15: Re-phase cost to achieve into the following financial year for initiatives that are not on the critical path | J15: 42678 | K15: Open | L15: Stable | M15: Steering Committee
A16: R-12 | B16: Reporting arrives at the office in six different formats and reconciliation consumes the analyst capacity that should go into analysis | C16: WS1 Finance | D16: S. Lindqvist | E16: 5 | F16: 2 | G16: =E16*F16 -> 10 | H16: =IF(G16>=25,"Critical",IF(G16>=15,"High",IF(G16>=8,"Medium","Low"))) -> Medium | I16: Mandate the tracker as the single source, accept slide input only as commentary | J16: 42650 | K16: In progress | L16: Stable
A17: R-13 | B17: Pension obligation at the target is larger than the baseline assumes | C17: WS1 Finance | D17: R. Whitfield | E17: 2 | F17: 4 | G17: =E17*F17 -> 8 | H17: =IF(G17>=25,"Critical",IF(G17>=15,"High",IF(G17>=8,"Medium","Low"))) -> Medium | I17: Commission an actuarial review before the opening balance sheet is finalised | J17: 42650 | K17: Open | L17: Stable
A18: R-14 | B18: Rebranding at customer-facing sites is not complete before the flagship event | C18: WS7 Real Estate | D18: F. Ricciardi | E18: 2 | F18: 2 | G18: =E18*F18 -> 4 | H18: =IF(G18>=25,"Critical",IF(G18>=15,"High",IF(G18>=8,"Medium","Low"))) -> Low | I18: Prioritise tier 1 sites and event venues, accept a phased schedule elsewhere | J18: 42657 | K18: In progress | L18: Decreasing

Sheet Assumptions
A1: Assumption Register
A2: Assumptions the plan depends on and their validation status, 29 September 2016
A4: Assumption ID | B4: Assumption | C4: Workstream | D4: Date made | E4: Impact if invalid | F4: Validation action | G4: Validate by | H4: Validation status
A5: AS-01 | B5: The legacy ERP maintenance agreement at the target can be exited on three months notice | C5: WS3 IT | D5: 42594 | E5: ERP decommissioning slips by up to nine months and the licence synergy in S-04 is lost | F5: Legal to review the maintenance clause and confirm the notice period | G5: 42650 | H5: Open
A6: AS-02 | B6: No further regulatory condition applies to the EMEA entity mergers | C6: WS2 Tax | D6: 42601 | E6: Entity rationalisation and the transfer pricing model both slip | F6: External counsel to confirm per jurisdiction | G6: 42657 | H6: Open
A7: AS-03 | B7: Retention acceptance among named critical roles will exceed 85 percent | C7: WS4 Human Capital | D7: 42608 | E7: Coverage model and account continuity are both exposed | F7: Track acceptance weekly and report at Day 30 | G7: 42650 | H7: Open
A8: AS-04 | B8: Supplier contracts contain no change of control clause that blocks renegotiation | C8: WS5 Supply Chain | D8: 42615 | E8: Procurement synergy wave 1 cannot be booked in the current financial year | F8: Contract review for the top 12 logistics providers | G8: 42657 | H8: Confirmed
A9: AS-05 | B9: The flagship event date of 18 to 20 October is immovable | C9: WS6 Go-to-Market | D9: 42587 | E9: Portfolio and narrative milestones lose their forcing function | F9: None, treated as fixed | G9: 42620 | H9: Confirmed
A10: AS-06 | B10: Integration spend approved at close remains available in full | C10: WS1 Finance | D10: 42620 | E10: Cost to achieve must be re-phased and synergy delivery moves right | F10: Confirm with treasury at the first combined quarter end | G10: 42664 | H10: Open

Sheet Issues
A1: Issue Log
A2: Risks that have materialised and problems already occurring, 29 September 2016
A4: Issue ID | B4: Issue description | C4: Originating risk | D4: Date raised | E4: Workstream | F4: Owner | G4: Severity | H4: Impact on milestone | I4: Resolution action | J4: Target date | K4: Status | L4: Escalated to
A5: I-01 | B5: Material master extract from the target is incomplete; 18 percent of records are missing mandatory fields | C5: R-03 | D5: 42635 | E5: WS3 IT | F5: G. Aydin | G5: High | H5: M-07 blueprint sign-off | I5: Re-extract with corrected field mapping and a data quality gate | J5: 42648 | K5: In progress | L5: VCIO
A6: I-02 | B6: The EMEA entity chain tax review has passed its due date and now blocks the rationalisation plan | C6: R-06 | D6: 42639 | E6: WS2 Tax | F6: N. Devereux | G6: High | H6: M-05 entity plan approval | I6: Escalated to the Steering Committee with a named completion date | J6: 42646 | K6: Open | L6: Steering Committee
A7: I-03 | B7: Reported secured synergy exceeded the Finance-validated figure in the session 01 pack | C7: - | D7: 42628 | E7: WS1 Finance | F7: M. Haddad | G7: Medium | H7: Credibility of the value case | I7: Only Finance-validated initiatives are counted from session 02 onward, per decision B-06 | J7: 42641 | K7: Resolved
A8: I-04 | B8: Two field organisations called on the same 40 named accounts in the first fortnight | C8: R-09 | D8: 42632 | E8: WS6 Go-to-Market | F8: L. Kowalczyk | G8: Medium | H8: Customer experience ahead of the flagship event | I8: Interim account ownership list published weekly | J8: 42639 | K8: Resolved
A9: I-05 | B9: The role holder table still names the previous Human Capital workstream lead | C9: - | D9: 42633 | E9: WS4 Human Capital | F9: D. Okonjo | G9: Low | H9: Ownership clarity | I9: Update the role holder table and reconcile it against the role cards | J9: 42643 | K9: In progress

Sheet Dependencies
A1: Dependency Register
A2: Cross-workstream handovers | decision B-03 requires both leads to confirm | 2 still one-sided
A4: Dependency ID | B4: Deliverable handed over | C4: From workstream | D4: From owner | E4: To workstream | F4: To owner | G4: Needed by | H4: Criticality | I4: Both leads confirmed | J4: Status
A5: D-01 | B5: Approved legal entity structure required to fix the consolidation scope | C5: WS2 Tax | D5: N. Devereux | E5: WS1 Finance | F5: R. Whitfield | G5: 42655 | H5: Critical | I5: No | J5: At risk
A6: D-02 | B6: ERP target system decision required before the material master re-extract | C6: WS3 IT | D6: T. Bergström | E6: WS5 Supply Chain | F6: K. Matsuda | G6: 42646 | H6: Critical | I6: Yes | J6: Delayed
A7: D-03 | B7: Works council conclusion required before the organisation structure release | C7: WS4 Human Capital | D7: J. Adeyemi | E7: WS4 Human Capital | F7: J. Adeyemi | G7: 42671 | H7: Critical | I7: Yes | J7: At risk
A8: D-04 | B8: Compensation plan design required before territory and quota alignment | C8: WS4 Human Capital | D8: J. Adeyemi | E8: WS6 Go-to-Market | F8: L. Kowalczyk | G8: 42654 | H8: High | I8: Yes | J8: On track
A9: D-05 | B9: Spend cube required before logistics renegotiation can be scoped | C9: WS5 Supply Chain | D9: K. Matsuda | E9: WS5 Supply Chain | F9: K. Matsuda | G9: 42657 | H9: High | I9: Yes | J9: On track
A10: D-06 | B10: Lease expiry analysis required before the EMEA site plan is approved | C10: WS7 Real Estate | D10: F. Ricciardi | E10: WS7 Real Estate | F10: F. Ricciardi | G10: 42664 | H10: Medium | I10: Yes | J10: On track
A11: D-07 | B11: Entity plan required before transfer pricing documentation can begin | C11: WS2 Tax | D11: N. Devereux | E11: WS2 Tax | F11: N. Devereux | G11: 42655 | H11: High | I11: No | J11: At risk
A12: D-08 | B12: Portfolio cross-reference required before the flagship event narrative | C12: WS6 Go-to-Market | D12: L. Kowalczyk | E12: WS6 Go-to-Market | F12: L. Kowalczyk | G12: 42654 | H12: High | I12: Yes | J12: On track

Sheet Summary
A1: RAID Summary
A2: Calculates automatically from the four registers. No input.
A4: Risks by severity band
A5: Band | B5: Number | C5: Share
A6: Low | B6: =COUNTIF(Risks!$H$5:$H$18,$A6) -> 2 | C6: =IFERROR($B6/$B$10,"") -> 0.14285714
A7: Medium | B7: =COUNTIF(Risks!$H$5:$H$18,$A7) -> 9 | C7: =IFERROR($B7/$B$10,"") -> 0.64285714
A8: High | B8: =COUNTIF(Risks!$H$5:$H$18,$A8) -> 3 | C8: =IFERROR($B8/$B$10,"") -> 0.21428571
A9: Critical | B9: =COUNTIF(Risks!$H$5:$H$18,$A9) -> 0 | C9: =IFERROR($B9/$B$10,"") -> 0
A10: Total | B10: =SUM($B$6:$B$9) -> 14
A12: RAID volume
A13: Open risks | B13: =COUNTIF(Risks!$K$5:$K$18,"Open")+COUNTIF(Risks!$K$5:$K$18,"In progress") -> 14
A14: Risks at or above severity 15 | B14: =COUNTIF(Risks!$G$5:$G$18,">=15") -> 3
A15: Risks escalated beyond the workstream | B15: =COUNTIF(Risks!$M$5:$M$18,"Steering Committee")+COUNTIF(Risks!$M$5:$M$18,"VCIO") -> 6
A16: Open assumptions | B16: =COUNTIF(Assumptions!$H$5:$H$10,"Open") -> 4
A17: Open issues | B17: =COUNTIF(Issues!$K$5:$K$9,"Open")+COUNTIF(Issues!$K$5:$K$9,"In progress") -> 3
A18: Dependencies at risk or delayed | B18: =COUNTIF(Dependencies!$J$5:$J$12,"At risk")+COUNTIF(Dependencies!$J$5:$J$12,"Delayed") -> 4
A19: Critical or high dependencies not confirmed by both leads | B19: =COUNTIFS(Dependencies!$H$5:$H$12,"Critical",Dependencies!$I$5:$I$12,"No")+COUNTIFS(Dependencies!$H$5:$H$12,"High",Dependencies!$I$5:$I$12,"No") -> 2
